{
  "items": [
    {
      "id": "itm_1",
      "referenceId": "ITM-356110",
      "code": "I000035611",
      "skuCode": "APL-MM2-WHT",
      "description": "APPLE MAGIC MOUSE 2, BLUETOOTH, RECHARGEABLE",
      "itemGroup": "EQUIPMENT",
      "category": "Apple Mac Accy",
      "subCategory": "Magic Mouse",
      "type": "Peripherals",
      "brand": "APPLE",
      "subBrand": "Mac",
      "supplierModelCode": "MM2-A1657",
      "itiModelCode": "ITI-MM2-001",
      "modelCode": "A1657",
      "uom": "PCS",
      "color": "White",
      "warrantyDuration": 1,
      "warrantyDurationType": "Years",
      "trade": true,
      "withSerial": true,
      "nonTrade": false,
      "bundle": false,
      "nonInventoriable": false,
      "srp": 4990,
      "currency": "PHP",
      "currentBalance": 14,
      "reorderLevel": 8,
      "standardPack": 1,
      "status": "Active",
      "bom": [],
      "createdAt": "2026-01-10T00:00:00.000Z",
      "updatedAt": "2026-01-10T00:00:00.000Z"
    },
    {
      "id": "itm_2",
      "referenceId": "ITM-356111",
      "code": "I000035612",
      "skuCode": "APL-MKB-USBC",
      "description": "APPLE MAGIC KEYBOARD WITH TOUCH ID",
      "itemGroup": "EQUIPMENT",
      "category": "Apple Mac Accy",
      "subCategory": "Keyboard",
      "type": "Peripherals",
      "brand": "APPLE",
      "subBrand": "Mac",
      "supplierModelCode": "MKB-TID",
      "itiModelCode": "ITI-MKB-002",
      "modelCode": "MK293ZA/A",
      "uom": "PCS",
      "color": "Silver",
      "warrantyDuration": 1,
      "warrantyDurationType": "Years",
      "trade": true,
      "withSerial": true,
      "nonTrade": false,
      "bundle": false,
      "nonInventoriable": false,
      "srp": 8990,
      "currency": "PHP",
      "currentBalance": 6,
      "reorderLevel": 10,
      "standardPack": 1,
      "status": "Active",
      "bom": [],
      "createdAt": "2026-01-12T00:00:00.000Z",
      "updatedAt": "2026-01-12T00:00:00.000Z"
    },
    {
      "id": "itm_3",
      "referenceId": "ITM-356112",
      "code": "I000035613",
      "skuCode": "DELL-U2723QE",
      "description": "DELL ULTRASHARP 27 4K USB-C HUB MONITOR",
      "itemGroup": "EQUIPMENT",
      "category": "Monitors",
      "subCategory": "4K Monitor",
      "type": "Display",
      "brand": "DELL",
      "subBrand": "UltraSharp",
      "supplierModelCode": "U2723QE",
      "itiModelCode": "ITI-MON-003",
      "modelCode": "U2723QE",
      "uom": "PCS",
      "color": "Black",
      "warrantyDuration": 3,
      "warrantyDurationType": "Years",
      "trade": true,
      "withSerial": true,
      "nonTrade": false,
      "bundle": false,
      "nonInventoriable": false,
      "srp": 42890,
      "currency": "PHP",
      "currentBalance": 4,
      "reorderLevel": 5,
      "standardPack": 1,
      "status": "Active",
      "bom": [],
      "createdAt": "2026-01-15T00:00:00.000Z",
      "updatedAt": "2026-01-15T00:00:00.000Z"
    },
    {
      "id": "itm_4",
      "referenceId": "ITM-356113",
      "code": "I000035614",
      "skuCode": "LOGI-MX3S",
      "description": "LOGITECH MX MASTER 3S PERFORMANCE WIRELESS MOUSE",
      "itemGroup": "EQUIPMENT",
      "category": "Peripherals",
      "subCategory": "Mouse",
      "type": "Accessories",
      "brand": "LOGITECH",
      "subBrand": "MX",
      "supplierModelCode": "MX3S",
      "itiModelCode": "ITI-MSE-004",
      "modelCode": "MX Master 3S",
      "uom": "PCS",
      "color": "Graphite",
      "warrantyDuration": 2,
      "warrantyDurationType": "Years",
      "trade": true,
      "withSerial": true,
      "nonTrade": false,
      "bundle": false,
      "nonInventoriable": false,
      "srp": 6590,
      "currency": "PHP",
      "currentBalance": 20,
      "reorderLevel": 12,
      "standardPack": 1,
      "status": "Active",
      "bom": [],
      "createdAt": "2026-01-15T00:00:00.000Z",
      "updatedAt": "2026-01-15T00:00:00.000Z"
    },
    {
      "id": "itm_5",
      "referenceId": "ITM-356114",
      "code": "I000035615",
      "skuCode": "CAT6-UTP-305",
      "description": "CATEGORY 6 UTP CABLE 305M BOX",
      "itemGroup": "RAW MATERIAL",
      "category": "Cabling",
      "subCategory": "Network Cable",
      "type": "Infrastructure",
      "brand": "AMP",
      "subBrand": "NETCONNECT",
      "supplierModelCode": "CAT6-305",
      "itiModelCode": "ITI-CBL-005",
      "modelCode": "CAT6-UTP",
      "uom": "BOX",
      "color": "Blue",
      "warrantyDuration": 0,
      "warrantyDurationType": "Months",
      "trade": false,
      "withSerial": false,
      "nonTrade": true,
      "bundle": false,
      "nonInventoriable": false,
      "srp": 5850,
      "currency": "PHP",
      "currentBalance": 2,
      "reorderLevel": 4,
      "standardPack": 1,
      "status": "Active",
      "bom": [],
      "createdAt": "2026-01-16T00:00:00.000Z",
      "updatedAt": "2026-01-16T00:00:00.000Z"
    },
    {
      "id": "itm_6",
      "referenceId": "ITM-356115",
      "code": "I000035616",
      "skuCode": "BATT-AA-ALK",
      "description": "ALKALINE BATTERY AA 4-PACK",
      "itemGroup": "CONSUMABLE",
      "category": "Power",
      "subCategory": "Battery",
      "type": "Consumables",
      "brand": "ENERGIZER",
      "subBrand": "MAX",
      "supplierModelCode": "AA-4",
      "itiModelCode": "ITI-BAT-006",
      "modelCode": "E91BP4",
      "uom": "PACK",
      "color": "Silver",
      "warrantyDuration": 0,
      "warrantyDurationType": "Months",
      "trade": false,
      "withSerial": false,
      "nonTrade": true,
      "bundle": false,
      "nonInventoriable": false,
      "srp": 220,
      "currency": "PHP",
      "currentBalance": 45,
      "reorderLevel": 20,
      "standardPack": 10,
      "status": "Active",
      "bom": [],
      "createdAt": "2026-01-18T00:00:00.000Z",
      "updatedAt": "2026-01-18T00:00:00.000Z"
    },
    {
      "id": "itm_7",
      "referenceId": "ITM-356116",
      "code": "I000035617",
      "skuCode": "NBK-DELL-14",
      "description": "DELL LATITUDE 5440 i7 16GB 512GB SSD",
      "itemGroup": "EQUIPMENT",
      "category": "Laptops",
      "subCategory": "Business Laptop",
      "type": "Computing",
      "brand": "DELL",
      "subBrand": "Latitude",
      "supplierModelCode": "LAT5440",
      "itiModelCode": "ITI-NBK-007",
      "modelCode": "Latitude 5440",
      "uom": "PCS",
      "color": "Gray",
      "warrantyDuration": 3,
      "warrantyDurationType": "Years",
      "trade": true,
      "withSerial": true,
      "nonTrade": false,
      "bundle": false,
      "nonInventoriable": false,
      "srp": 69800,
      "currency": "PHP",
      "currentBalance": 3,
      "reorderLevel": 3,
      "standardPack": 1,
      "status": "Active",
      "bom": [],
      "createdAt": "2026-01-20T00:00:00.000Z",
      "updatedAt": "2026-01-20T00:00:00.000Z"
    },
    {
      "id": "itm_8",
      "referenceId": "ITM-356117",
      "code": "I000035618",
      "skuCode": "USB-C-HUB-7IN1",
      "description": "7-IN-1 USB-C HUB HDMI + LAN + PD",
      "itemGroup": "CONSUMABLE",
      "category": "Adapters",
      "subCategory": "USB Hub",
      "type": "Accessories",
      "brand": "UGREEN",
      "subBrand": "CM511",
      "supplierModelCode": "CM511",
      "itiModelCode": "ITI-HUB-008",
      "modelCode": "CM511",
      "uom": "PCS",
      "color": "Space Gray",
      "warrantyDuration": 1,
      "warrantyDurationType": "Years",
      "trade": true,
      "withSerial": false,
      "nonTrade": false,
      "bundle": false,
      "nonInventoriable": false,
      "srp": 2390,
      "currency": "PHP",
      "currentBalance": 18,
      "reorderLevel": 6,
      "standardPack": 1,
      "status": "Active",
      "bom": [],
      "createdAt": "2026-01-22T00:00:00.000Z",
      "updatedAt": "2026-01-22T00:00:00.000Z"
    }
  ],
  "suppliers": [
    {
      "id": "sup_1",
      "referenceId": "SUP-100001",
      "code": "S000001",
      "registeredName": "CRIF PHILIPPINES, INC.",
      "tradeName": "CRIF Philippines",
      "parentCompany": "CRIF S.P.A.",
      "fullAddress": "26th Floor BDO Equitable Tower, 8751 Paseo de Roxas, Makati City, NCR",
      "telNo": "(02) 5318 8000",
      "faxNo": "(02) 5318 8001",
      "paymentTerm": "30 DAYS",
      "active": true,
      "tin": "009-863-512-000",
      "ewt": "2%",
      "currency": "PHP",
      "creditLimit": 2500000,
      "businessStyle": "IT Services",
      "taxScheme": "VAT",
      "bdm": "Angela Cruz",
      "walkIn": false,
      "imported": true
    },
    {
      "id": "sup_2",
      "referenceId": "SUP-100002",
      "code": "S000002",
      "registeredName": "ASIA PACIFIC COMPUTERS INC.",
      "tradeName": "APC",
      "parentCompany": "",
      "fullAddress": "3rd Floor Cyberzone Building, Bonifacio Global City, Taguig, NCR",
      "telNo": "(02) 8890 2211",
      "faxNo": "",
      "paymentTerm": "15 DAYS",
      "active": true,
      "tin": "235-447-101-000",
      "ewt": "1%",
      "currency": "PHP",
      "creditLimit": 1800000,
      "businessStyle": "Hardware Distribution",
      "taxScheme": "VAT",
      "bdm": "Paolo Santos",
      "walkIn": false,
      "imported": false
    },
    {
      "id": "sup_3",
      "referenceId": "SUP-100003",
      "code": "S000003",
      "registeredName": "LUNA OFFICE SUPPLIES TRADING",
      "tradeName": "Luna Office",
      "parentCompany": "",
      "fullAddress": "Blk 12 Lot 4 Commonwealth Ave, Quezon City, NCR",
      "telNo": "(02) 8455 9012",
      "faxNo": "",
      "paymentTerm": "COD",
      "active": true,
      "tin": "182-336-098-000",
      "ewt": "0%",
      "currency": "PHP",
      "creditLimit": 300000,
      "businessStyle": "Office Supplies",
      "taxScheme": "NON-VAT",
      "bdm": "Mika Dizon",
      "walkIn": true,
      "imported": false
    },
    {
      "id": "sup_4",
      "referenceId": "SUP-100004",
      "code": "S000004",
      "registeredName": "MANILA TECH IMPORTS CORPORATION",
      "tradeName": "MTIC",
      "parentCompany": "",
      "fullAddress": "2278 Chino Roces Ave, Makati City, NCR",
      "telNo": "(02) 8777 2210",
      "faxNo": "",
      "paymentTerm": "45 DAYS",
      "active": true,
      "tin": "304-887-120-000",
      "ewt": "2%",
      "currency": "PHP",
      "creditLimit": 3500000,
      "businessStyle": "Importer",
      "taxScheme": "VAT",
      "bdm": "Jared Lim",
      "walkIn": false,
      "imported": true
    }
  ],
  "customers": [
    {
      "id": "cus_1",
      "referenceId": "CUS-200001",
      "code": "C000001",
      "registeredName": "COASTAL PARADISE LEISURE INC.",
      "tradeName": "Coastal Paradise",
      "parentCompany": "",
      "fullAddress": "Unit 1805 EDSA Corner Aurora Blvd, Cubao, Quezon City, NCR",
      "telNo": "(02) 8551 4455",
      "faxNo": "",
      "paymentTerm": "15 DAYS",
      "active": true,
      "tin": "010-254-149-000",
      "ewt": "1%",
      "currency": "PHP",
      "creditLimit": 1500000,
      "businessStyle": "Hospitality",
      "taxScheme": "VAT",
      "bdm": "Rhea Velasco",
      "walkIn": false,
      "imported": false
    },
    {
      "id": "cus_2",
      "referenceId": "CUS-200002",
      "code": "C000002",
      "registeredName": "NOVA PRIME CONSTRUCTION CORP.",
      "tradeName": "Nova Prime",
      "parentCompany": "",
      "fullAddress": "5F One San Miguel Ave, Ortigas Center, Pasig, NCR",
      "telNo": "(02) 8228 1190",
      "faxNo": "",
      "paymentTerm": "30 DAYS",
      "active": true,
      "tin": "742-995-030-000",
      "ewt": "2%",
      "currency": "PHP",
      "creditLimit": 2250000,
      "businessStyle": "Construction",
      "taxScheme": "VAT",
      "bdm": "Nikko Reyes",
      "walkIn": false,
      "imported": false
    },
    {
      "id": "cus_3",
      "referenceId": "CUS-200003",
      "code": "C000003",
      "registeredName": "TAGUIG URBAN HEALTHCARE FOUNDATION",
      "tradeName": "TUHF",
      "parentCompany": "",
      "fullAddress": "12 Bayani Road, Western Bicutan, Taguig, NCR",
      "telNo": "(02) 7999 3411",
      "faxNo": "",
      "paymentTerm": "30 DAYS",
      "active": true,
      "tin": "538-229-441-000",
      "ewt": "1%",
      "currency": "PHP",
      "creditLimit": 1900000,
      "businessStyle": "Healthcare",
      "taxScheme": "VAT",
      "bdm": "Gina Paredes",
      "walkIn": false,
      "imported": false
    },
    {
      "id": "cus_4",
      "referenceId": "CUS-200004",
      "code": "C000004",
      "registeredName": "METRO LEARNING HUBS INC.",
      "tradeName": "Metro Learning",
      "parentCompany": "",
      "fullAddress": "17 Scout Borromeo St, South Triangle, Quezon City, NCR",
      "telNo": "(02) 8374 2515",
      "faxNo": "",
      "paymentTerm": "COD",
      "active": true,
      "tin": "668-113-290-000",
      "ewt": "0%",
      "currency": "PHP",
      "creditLimit": 600000,
      "businessStyle": "Education",
      "taxScheme": "NON-VAT",
      "bdm": "Lia Ramos",
      "walkIn": true,
      "imported": false
    }
  ]
}
